LICENSE
MANIFEST.in
README.rst
setup.cfg
setup.py
Beaker.egg-info/PKG-INFO
Beaker.egg-info/SOURCES.txt
Beaker.egg-info/dependency_links.txt
Beaker.egg-info/entry_points.txt
Beaker.egg-info/not-zip-safe
Beaker.egg-info/requires.txt
Beaker.egg-info/top_level.txt
beaker/__init__.py
beaker/_compat.py
beaker/cache.py
beaker/container.py
beaker/converters.py
beaker/cookie.py
beaker/exceptions.py
beaker/middleware.py
beaker/session.py
beaker/synchronization.py
beaker/util.py
beaker/crypto/__init__.py
beaker/crypto/jcecrypto.py
beaker/crypto/noencryption.py
beaker/crypto/nsscrypto.py
beaker/crypto/pbkdf2.py
beaker/crypto/pyca_cryptography.py
beaker/crypto/pycrypto.py
beaker/crypto/util.py
beaker/ext/__init__.py
beaker/ext/database.py
beaker/ext/google.py
beaker/ext/memcached.py
beaker/ext/mongodb.py
beaker/ext/redisclusternm.py
beaker/ext/redisnm.py
beaker/ext/sqla.py
tests/__init__.py
tests/annotated_functions.py
tests/test_cache.py
tests/test_cache_decorator.py
tests/test_cachemanager.py
tests/test_container.py
tests/test_converters.py
tests/test_cookie_domain_only.py
tests/test_cookie_expires.py
tests/test_cookie_only.py
tests/test_database.py
tests/test_domain_setting.py
tests/test_increment.py
tests/test_memcached.py
tests/test_namespacing.py
tests/test_pbkdf2.py
tests/test_session.py
tests/test_sqla.py
tests/test_syncdict.py
tests/test_synchronizer.py
tests/test_unicode_cache_keys.py
tests/test_managers/__init__.py
tests/test_managers/base.py
tests/test_managers/test_ext_mongodb.py
tests/test_managers/test_ext_redis.py
tests/test_managers/test_ext_rediscluster.py
tests/test_namespacing_files/__init__.py
tests/test_namespacing_files/namespace_get.py
tests/test_namespacing_files/namespace_go.py