Metadata-Version: 2.1
Name: Beaker
Version: 1.13.0
Summary: A Session and Caching library with WSGI Middleware
Home-page: https://beaker.readthedocs.io/
Author: Ben Bangert, Mike Bayer, Philip Jenvey, Alessandro Molina
Author-email: ben@groovie.org, pjenvey@groovie.org, amol@turbogears.org
License: BSD
Keywords: wsgi myghty session web cache middleware
Platform: UNKNOWN
Classifier: Development Status :: 5 - Production/Stable
Classifier: Environment :: Web Environment
Classifier: Intended Audience :: Developers
Classifier: License :: OSI Approved :: BSD License
Classifier: Programming Language :: Python
Classifier: Programming Language :: Python :: 3.7
Classifier: Programming Language :: Python :: 3.8
Classifier: Programming Language :: Python :: 3.9
Classifier: Programming Language :: Python :: 3.10
Classifier: Programming Language :: Python :: 3.11
Classifier: Topic :: Internet :: WWW/HTTP :: Dynamic Content
Classifier: Topic :: Internet :: WWW/HTTP :: Dynamic Content
Classifier: Topic :: Internet :: WWW/HTTP :: Dynamic Content
Classifier: Topic :: Internet :: WWW/HTTP :: WSGI
Classifier: Topic :: Internet :: WWW/HTTP :: WSGI :: Middleware
Provides-Extra: crypto
Provides-Extra: cryptography
Provides-Extra: pycrypto
Provides-Extra: pycryptodome
Provides-Extra: testsuite
License-File: LICENSE
